Metadata-Version: 2.1
Name: SCOIT
Version: 0.1.2.1
Summary: SCOIT is an implementation of a probabilistic tensor decomposition framework for single-cell multi-omics data integration.
Home-page: https://github.com/deepomicslab/SCOIT
Author: WANG Ruohan
Author-email: ruohawang2-c@my.cityu.edu.hk
License: MIT
Classifier: Programming Language :: Python :: 3
Classifier: License :: OSI Approved :: MIT License
Classifier: Programming Language :: Python :: 3.8
Requires-Python: >=3.6
License-File: LICENSE
